opentsp/__init__.py
opentsp/exampleHypothesisTests.py
opentsp/helpers.py
opentsp/objects.py
opentsp/reducers.py
opentsp/runtests.py
opentsp-1.1.3.dist-info/METADATA
opentsp-1.1.3.dist-info/RECORD
opentsp-1.1.3.dist-info/WHEEL
opentsp-1.1.3.dist-info/top_level.txt
