Metadata-Version: 2.1
Name: opentsp
Version: 1.1.3
Summary: Generate TSP instances and test hypotheses on them
Home-page: UNKNOWN
Author: James Langbein
Author-email: james.langbein@protonmail.com
License: MIT
Platform: UNKNOWN
Classifier: License :: OSI Approved :: MIT License
Classifier: Programming Language :: Python
Classifier: Programming Language :: Python :: 3
Classifier: Programming Language :: Python :: 3.6
Classifier: Development Status :: 4 - Beta
Requires-Dist: matplotlib
Requires-Dist: numpy
